bootstrap/__init__.py
bootstrap/bootstrap.py
bootstrap/storage.py
bootstrap/utils.py
service_bootstrap-0.0.5.dist-info/LICENSE
service_bootstrap-0.0.5.dist-info/METADATA
service_bootstrap-0.0.5.dist-info/WHEEL
service_bootstrap-0.0.5.dist-info/top_level.txt
service_bootstrap-0.0.5.dist-info/RECORD
