Metadata-Version: 2.1
Name: service-bootstrap
Version: 0.0.5
Summary: Framework for setting up service
Home-page: https://github.com/rzarajczyk/service-bootstrap
Author: Rafał Zarajczyk
Author-email: rzarajczyk@gmail.com
Classifier: Programming Language :: Python :: 3
Classifier: License :: OSI Approved :: MIT License
Classifier: Operating System :: OS Independent
License-File: LICENSE
Requires-Dist: pyyaml (~=6.0)
Requires-Dist: tzlocal
Requires-Dist: pytz
